facenet_pytorch/__init__.py
facenet_pytorch/test.py
facenet_pytorch/data/onet.pt
facenet_pytorch/data/pnet.pt
facenet_pytorch/data/rnet.pt
facenet_pytorch/models/inception_resnet_v1.py
facenet_pytorch/models/mtcnn.py
facenet_pytorch/models/utils/detect_face.py
facenet_pytorch/models/utils/download.py
facenet_pytorch/models/utils/tensorflow2pytorch.py
facenet_pytorch/models/utils/training.py
facenet_pytorch-2.5.3.dist-info/LICENSE.md
facenet_pytorch-2.5.3.dist-info/METADATA
facenet_pytorch-2.5.3.dist-info/WHEEL
facenet_pytorch-2.5.3.dist-info/top_level.txt
facenet_pytorch-2.5.3.dist-info/RECORD
