Metadata-Version: 2.1
Name: facenet-pytorch
Version: 2.5.3
Summary: Pretrained Pytorch face detection and recognition models
Home-page: https://github.com/timesler/facenet-pytorch
Author: Tim Esler
Author-email: tim.esler@gmail.com
Classifier: Programming Language :: Python :: 3
Classifier: License :: OSI Approved :: MIT License
Classifier: Operating System :: OS Independent
License-File: LICENSE.md
